solvex/__init__.py
solvex/explainer.py
solvex/masker.py
solvex-1.0.3.dist-info/LICENSE
solvex-1.0.3.dist-info/METADATA
solvex-1.0.3.dist-info/WHEEL
solvex-1.0.3.dist-info/top_level.txt
solvex-1.0.3.dist-info/RECORD
