Metadata-Version: 2.1
Name: solvex
Version: 1.0.3
Summary: Solvability-Based Explainer
Author-email: Yilun Zhou <yilun@csail.mit.edu>
Project-URL: Homepage, https://yilunzhou.github.io/solvability/
Project-URL: Bug Tracker, https://github.com/yilunzhou/solvability-explainer/issues
Classifier: Programming Language :: Python :: 3
Classifier: License :: OSI Approved :: MIT License
Classifier: Operating System :: OS Independent
Classifier: Topic :: Scientific/Engineering :: Artificial Intelligence
Classifier: Intended Audience :: Science/Research
Classifier: Development Status :: 5 - Production/Stable
Requires-Python: >=3.7
License-File: LICENSE
Requires-Dist: tqdm
Requires-Dist: tabulate (>=0.9.0)
Requires-Dist: numpy
Requires-Dist: matplotlib
Requires-Dist: Pillow
Requires-Dist: torch
Requires-Dist: spacy
